isotonic_estimator_lib/__init__.py
isotonic_estimator_lib/isotonic_estimator.py
isotonic_estimator_lib/tester_quality.py
isotonic_estimator_lib-0.0.7.dist-info/LICENSE
isotonic_estimator_lib-0.0.7.dist-info/METADATA
isotonic_estimator_lib-0.0.7.dist-info/WHEEL
isotonic_estimator_lib-0.0.7.dist-info/top_level.txt
isotonic_estimator_lib-0.0.7.dist-info/RECORD
