Metadata-Version: 2.1
Name: isotonic-estimator-lib
Version: 0.0.7
Summary: Package that implements the isotonic estimator for Wicksell's problem.
Author-email: Wicksell Isotonic Estimator <f.gili@tudelft.nl>
Classifier: Programming Language :: Python :: 3
Classifier: License :: OSI Approved :: MIT License
Classifier: Operating System :: OS Independent
Requires-Python: >=3.7
License-File: LICENSE
